ui_test_runner/__init__.py
ui_test_runner/main.py
ui_test_runner-0.0.2.dist-info/METADATA
ui_test_runner-0.0.2.dist-info/WHEEL
ui_test_runner-0.0.2.dist-info/top_level.txt
ui_test_runner-0.0.2.dist-info/RECORD
