Metadata-Version: 2.1
Name: ui-test-runner
Version: 0.0.2
Summary: Translator UI Test Runner
Home-page: https://github.com/TranslatorSRI/UI_Test_Runner
Author: Max Wang
Author-email: max@covar.com
License: MIT
Requires-Python: >=3.9
Requires-Dist: jq >=1.6.0
Requires-Dist: httpx >=0.25.0
